alchemysdk/__init__.py
alchemysdk/api/api.py
alchemysdk/endpoints/nft.py
alchemysdk/endpoints/transfers.py
alchemysdk/types/nfts.py
alchemysdk/types/tokens.py
alchemysdk/types/transfers.py
alchemysdk-0.1.0.dist-info/LICENSE
alchemysdk-0.1.0.dist-info/WHEEL
alchemysdk-0.1.0.dist-info/METADATA
alchemysdk-0.1.0.dist-info/RECORD
