Metadata-Version: 2.1
Name: alchemysdk
Version: 0.1.0
Summary: An unofficial Python SDK for the Alchemy API
Home-page: https://github.com/FastestMolasses/alchemy-sdk
License: MIT
Keywords: opensea,api,sdk,python,nft,erc721,erc1155,ethereum,crypto,cryptocurrency,alchemy,web3,alchemy-sdk
Author: Abe M
Author-email: abe.malla8@gmail.com
Requires-Python: >=3.9,<4
Classifier: License :: OSI Approved :: MIT License
Classifier: Programming Language :: Python :: 3
Classifier: Programming Language :: Python :: 3.9
Classifier: Programming Language :: Python :: 3.10
Classifier: Programming Language :: Python :: 3.11
Requires-Dist: aiodns (>=3.0,<4.0)
Requires-Dist: aiohttp (>=3.8,<4.0)
Project-URL: Repository, https://github.com/FastestMolasses/alchemy-sdk
